MyDateTimeLib/__init__.py
MyDateTimeLib/myfunction.py
MyDateTimeLib/test_myfunctions.py
rsysDateTime001-0.1.2.dist-info/METADATA
rsysDateTime001-0.1.2.dist-info/WHEEL
rsysDateTime001-0.1.2.dist-info/top_level.txt
rsysDateTime001-0.1.2.dist-info/RECORD
